Workbook

Sheet WACC Dashboard
A1: (in millions) | B1: SYK | C1: JNJ | D1: ABT | E1: BSX | F1: EW
A2: Equity Value | B2: 134437.3 | C2: 499960.4 | D2: 217578.5 | E2: 141404.1 | F2: 49504.7
A3: Preferred Equity Value | B3: 0 | C3: 0 | D3: 0 | E3: 0 | F3: 0
A4: Short-Term Debt Value | B4: 1153 | C4: 8495 | D4: 3309 | E4: 389 | F4: 24.5
A5: Long-Term Debt Value | B5: 15207 | C5: 40838 | D5: 10827 | E5: 11583 | F5: 680.9
A6: Total Capital | B6: 150797.3 | C6: 549293.4 | D6: 231714.5 | E6: 153376.1 | F6: 50210.1 | H6: % Equity | I6: {=INDEX(B7:F7,$J$9)} -> 0.986
A7: % Equity | B7: 0.892 | C7: 0.91 | D7: 0.939 | E7: 0.922 | F7: 0.986 | H7: %Preferred Equity | I7: {=INDEX(B8:F8,$J$9)} -> 0
A8: %Preferred Equity | B8: 0 | C8: 0 | D8: 0 | E8: 0 | F8: 0 | H8: % Short-Term Debt | I8: {=INDEX(B9:F9,$J$9)} -> 0.0001
A9: % Short-Term Debt | B9: 0.008 | C9: 0.015 | D9: 0.014 | E9: 0.003 | F9: 0.0001 | H9: % Long-Term Debt | I9: {=INDEX(B10:F10,$J$9)} -> 0.014 | J9: 5
A10: % Long-Term Debt | B10: 0.101 | C10: 0.074 | D10: 0.047 | E10: 0.076 | F10: 0.014
A11: Beta | B11: =_xlfn.XLOOKUP(B1,'Beta Hand Calculations'!$A67:$A72,'Beta Hand Calculations'!$B67:$B72) -> 0.92256518 | C11: =_xlfn.XLOOKUP(C1,'Beta Hand Calculations'!$A67:$A72,'Beta Hand Calculations'!$B67:$B72) -> 0.3477213 | D11: =_xlfn.XLOOKUP(D1,'Beta Hand Calculations'!$A67:$A72,'Beta Hand Calculations'!$B67:$B72) -> 0.75981578 | E11: =_xlfn.XLOOKUP(E1,'Beta Hand Calculations'!$A67:$A72,'Beta Hand Calculations'!$B67:$B72) -> 0.73427617 | F11: =_xlfn.XLOOKUP(F1,'Beta Hand Calculations'!$A67:$A72,'Beta Hand Calculations'!$B67:$B72) -> 0.92220722
A12: Expected Return of Market | B12: =B13+B18 -> 0.09891
A13: Risk Free Rate | B13: {=(_xlfn.STOCKHISTORY("^TNX",TODAY(),TODAY(),2,0,1)) / 1000} -> 0.04391
A14: 2026 Tax Rate (%) | B14: 0.155 | C14: 0.18 | D14: 0.1626 | E14: 0.1168 | F14: 0.1723
A15: Pre-Tax Cost of Debt | B15: 0.039 | C15: 0.042 | D15: 0.041 | E15: 0.048 | F15: 0.045
A16: WACC | B16: =((B2/B6)*($B$13+(B11*$B$18)))+(((B4+B5)/B6)*B15)*(1-B14) -> 0.087957676 | C16: =((C2/C6)*($B$13+(C11*$B$18)))+(((C4+C5)/C6)*C15)*(1-C14) -> 0.060466534 | D16: =((D2/D6)*($B$13+(D11*$B$18)))+(((D4+D5)/D6)*D15)*(1-D14) -> 0.082566199 | E16: =((E2/E6)*($B$13+(E11*$B$18)))+(((E4+E5)/E6)*E15)*(1-E14) -> 0.081024499 | F16: =((F2/F6)*($B$13+(F11*$B$18)))+(((F4+F5)/F6)*F15)*(1-F14) -> 0.093825199
G17: Data compiled as of March 23rd, 2026
A18: Assumed Equity Risk Premium | B18: 0.055
A20: The Beta, Expected Market Return (and ERP), and Risk Free Rate are all manually calc'd, or pulled on the spot.I just came up with 5.5% as a conservative estimate, but it can be changed to whatever you want.

Sheet Beta Hand Calculations
A1: Dates (60 Months) | B1: SYK | C1: SYK Returns | D1: JNJ | E1: JNJ Returns | F1: ABT | G1: ABT Returns | H1: BSX | I1: BSX Returns | J1: EW | K1: EW Returns | L1: S&P 500 | M1: S&P Returns
A2: 44197 | B2: {=_xlfn.STOCKHISTORY(B$1,$A$2,$A$64,2,0,1)} -> 221.01 | C2: =B3/B2-1 -> 0.098095109 | D2: {=_xlfn.STOCKHISTORY(D$1,$A$2,$A$64,2,0,1)} -> 163.13 | E2: =D3/D2-1 -> -0.028627475 | F2: {=_xlfn.STOCKHISTORY(F$1,$A$2,$A$64,2,0,1)} -> 123.59 | G2: =F3/F2-1 -> -0.030827737 | H2: {=_xlfn.STOCKHISTORY(H$1,$A$2,$A$64,2,0,1)} -> 35.44 | I2: =H3/H2-1 -> 0.094243792 | J2: {=_xlfn.STOCKHISTORY(J$1,$A$2,$A$64,2,0,1)} -> 82.58 | K2: =J3/J2-1 -> 0.0062969242 | L2: 3714.24 | M2: =L3/L2-1 -> 0.026091475
A3: 44228 | B3: 242.69 | C3: =B4/B3-1 -> 0.0036672298 | D3: 158.46 | E3: =D4/D3-1 -> 0.037170264 | F3: 119.78 | G3: =F4/F3-1 -> 0.00050091835 | H3: 38.78 | I3: =H4/H3-1 -> -0.0033522434 | J3: 83.1 | K3: =J4/J3-1 -> 0.0064981949 | L3: 3811.15 | M3: =L4/L3-1 -> 0.042438634
A4: 44256 | B4: 243.58 | C4: =B5/B4-1 -> 0.078208391 | D4: 164.35 | E4: =D5/D4-1 -> -0.0098570125 | F4: 119.84 | G4: =F5/F4-1 -> 0.0020026702 | H4: 38.65 | I4: =H5/H4-1 -> 0.12807245 | J4: 83.64 | K4: =J5/J4-1 -> 0.1420373 | L4: 3972.89 | M4: =L5/L4-1 -> 0.052425313
A5: 44287 | B5: 262.63 | C5: =B6/B5-1 -> -0.028024217 | D5: 162.73 | E5: =D6/D5-1 -> 0.040066368 | F5: 120.08 | G5: =F6/F5-1 -> -0.02856429 | H5: 43.6 | I5: =H6/H5-1 -> -0.024082569 | J5: 95.52 | K5: =J6/J5-1 -> 0.0039782245 | L5: 4181.17 | M5: =L6/L5-1 -> 0.0054865026
A6: 44317 | B6: 255.27 | C6: =B7/B6-1 -> 0.017471697 | D6: 169.25 | E6: =D7/D6-1 -> -0.026646972 | F6: 116.65 | G6: =F7/F6-1 -> -0.0061723103 | H6: 42.55 | I6: =H7/H6-1 -> 0.0049353702 | J6: 95.9 | K6: =J7/J6-1 -> 0.079979145 | L6: 4204.11 | M6: =L7/L6-1 -> 0.022213976
A7: 44348 | B7: 259.73 | C7: =B8/B7-1 -> 0.043160205 | D7: 164.74 | E7: =D8/D7-1 -> 0.045283477 | F7: 115.93 | G7: =F8/F7-1 -> 0.043560769 | H7: 42.76 | I7: =H8/H7-1 -> 0.066417212 | J7: 103.57 | K7: =J8/J7-1 -> 0.084001159 | L7: 4297.5 | M7: =L8/L7-1 -> 0.022748109
A8: 44378 | B8: 270.94 | C8: =B9/B8-1 -> 0.022735661 | D8: 172.2 | E8: =D9/D8-1 -> 0.0054006969 | F8: 120.98 | G8: =F9/F8-1 -> 0.044552819 | H8: 45.6 | I8: =H9/H8-1 -> -0.0098684211 | J8: 112.27 | K8: =J9/J8-1 -> 0.043733856 | L8: 4395.26 | M8: =L9/L8-1 -> 0.028990321
A9: 44409 | B9: 277.1 | C9: =B10/B9-1 -> -0.048285817 | D9: 173.13 | E9: =D10/D9-1 -> -0.067174955 | F9: 126.37 | G9: =F10/F9-1 -> -0.065205349 | H9: 45.15 | I9: =H10/H9-1 -> -0.038981174 | J9: 117.18 | K9: =J10/J9-1 -> -0.033879502 | L9: 4522.68 | M9: =L10/L9-1 -> -0.04756914
A10: 44440 | B10: 263.72 | C10: =B11/B10-1 -> 0.0089109662 | D10: 161.5 | E10: =D11/D10-1 -> 0.0085448916 | F10: 118.13 | G10: =F11/F10-1 -> 0.091086092 | H10: 43.39 | I10: =H11/H10-1 -> -0.0059921641 | J10: 113.21 | K10: =J11/J10-1 -> 0.058387068 | L10: 4307.54 | M10: =L11/L10-1 -> 0.069143873
A11: 44470 | B11: 266.07 | C11: =B12/B11-1 -> -0.11064757 | D11: 162.88 | E11: =D12/D11-1 -> -0.04266945 | F11: 128.89 | G11: =F12/F11-1 -> -0.024206688 | H11: 43.13 | I11: =H12/H11-1 -> -0.11731973 | J11: 119.82 | K11: =J12/J11-1 -> -0.10440661 | L11: 4605.38 | M11: =L12/L11-1 -> -0.0083337314
A12: 44501 | B12: 236.63 | C12: =B13/B12-1 -> 0.13011875 | D12: 155.93 | E12: =D13/D12-1 -> 0.09709485 | F12: 125.77 | G12: =F13/F12-1 -> 0.11902679 | H12: 38.07 | I12: =H13/H12-1 -> 0.11583924 | J12: 107.31 | K12: =J13/J12-1 -> 0.20725002 | L12: 4567 | M12: =L13/L12-1 -> 0.043612875
A13: 44531 | B13: 267.42 | C13: =B14/B13-1 -> -0.072432877 | D13: 171.07 | E13: =D14/D13-1 -> 0.0071315836 | F13: 140.74 | G13: =F14/F13-1 -> -0.094358391 | H13: 42.48 | I13: =H14/H13-1 -> 0.0098870056 | J13: 129.55 | K13: =J14/J13-1 -> -0.15708221 | L13: 4766.18 | M13: =L14/L13-1 -> -0.052585089
A14: 44562 | B14: 248.05 | C14: =B15/B14-1 -> 0.061681113 | D14: 172.29 | E14: =D15/D14-1 -> -0.044808172 | F14: 127.46 | G14: =F15/F14-1 -> -0.053663895 | H14: 42.9 | I14: =H15/H14-1 -> 0.02960373 | J14: 109.2 | K14: =J15/J14-1 -> 0.029029304 | L14: 4515.55 | M14: =L15/L14-1 -> -0.031360521
... A63: 46054 | B63: 387.46 | C63: =B64/B63-1 -> -0.14161462 | D63: 248.43 | E63: =D64/D63-1 -> -0.052368877 | F63: 116.35 | G63: =F64/F63-1 -> -0.098839708 | H63: 76.85 | I63: =H64/H63-1 -> -0.095120364 | J63: 86.47 | K63: =J64/J63-1 -> -0.051462935 | L63: 6878.88 | M63: =L64/L63-1 -> -0.05413672
A64: 46082 | B64: 332.59 | D64: 235.42 | F64: 104.85 | H64: 69.54 | J64: 82.02 | L64: 6506.48
B66: Beta Vals: | L66: I have to paste S&P values since some stupid European stock keeps populating.
A67: =B1 -> SYK | B67: =SLOPE(C2:C63,$M$2:$M$63) -> 0.92256518
A68: =D1 -> JNJ | B68: =SLOPE(E2:E63,$M$2:$M$63) -> 0.3477213
A69: =F1 -> ABT | B69: =SLOPE(G2:G63,$M$2:$M$63) -> 0.75981578
A70: =H1 -> BSX | B70: =SLOPE(I2:I63,$M$2:$M$63) -> 0.73427617
A71: =J1 -> EW | B71: =SLOPE(K2:K63,$M$2:$M$63) -> 0.92220722
A72: =L1 -> S&P 500 | B72: =SLOPE(M2:M63,$M$2:$M$63) -> 1
